{"attackers":[{"alliance_id":99007599,"character_id":92521281,"corporation_id":98304186,"damage_done":3147,"security_status":-5.8,"ship_type_id":17930,"weapon_type_id":27371},{"alliance_id":99007599,"character_id":91931185,"corporation_id":98191559,"damage_done":848,"final_blow":true,"security_status":-0.9,"ship_type_id":17841,"weapon_type_id":3178},{"alliance_id":99008244,"character_id":91906104,"corporation_id":98561441,"security_status":-2,"ship_type_id":11186,"weapon_type_id":3244}],"killmail_id":71243873,"killmail_time":"2018-07-14T10:18:18-07:00","solar_system_id":30045338,"victim":{"alliance_id":99006625,"character_id":156917512,"corporation_id":98177721,"damage_taken":3995,"faction_id":500004,"items":[{"flag":12,"item_type_id":2605,"quantity_destroyed":1},{"flag":22,"item_type_id":14124,"quantity_destroyed":1},{"flag":29,"item_type_id":8091,"quantity_dropped":1},{"flag":87,"item_type_id":2488,"quantity_destroyed":2},{"flag":87,"item_type_id":2488,"quantity_dropped":1},{"flag":29,"item_type_id":27371,"quantity_destroyed":40},{"flag":21,"item_type_id":31928,"quantity_destroyed":1},{"flag":28,"item_type_id":8091,"quantity_dropped":1},{"flag":11,"item_type_id":2048,"quantity_destroyed":1},{"flag":19,"item_type_id":15889,"quantity_dropped":1},{"flag":20,"item_type_id":24417,"quantity_dropped":1},{"flag":93,"item_type_id":31105,"quantity_destroyed":1},{"flag":27,"item_type_id":27371,"quantity_dropped":40},{"flag":27,"item_type_id":8091,"quantity_dropped":1},{"flag":5,"item_type_id":28668,"quantity_destroyed":27},{"flag":94,"item_type_id":31364,"quantity_destroyed":1},{"flag":92,"item_type_id":31105,"quantity_destroyed":1},{"flag":28,"item_type_id":27371,"quantity_dropped":40},{"flag":5,"item_type_id":27371,"quantity_destroyed":667}],"position":{"x":1.1034387062468206e+12,"y":1.721617426112563e+11,"z":2.9245162899413984e+12},"ship_type_id":17930}}