{"attackers":[{"alliance_id":99001134,"character_id":1077050399,"corporation_id":98460931,"damage_done":20030,"final_blow":true,"security_status":1.9,"ship_type_id":29988,"weapon_type_id":3146}],"killmail_id":71244778,"killmail_time":"2018-07-14T11:13:24-07:00","solar_system_id":30002788,"victim":{"alliance_id":99006861,"character_id":2112269692,"corporation_id":98554535,"damage_taken":20030,"items":[{"flag":19,"item_type_id":3841,"quantity_dropped":1},{"flag":32,"item_type_id":12346,"quantity_destroyed":1},{"flag":31,"item_type_id":12346,"quantity_destroyed":1},{"flag":30,"item_type_id":12801,"quantity_dropped":66},{"flag":11,"item_type_id":2048,"quantity_dropped":1},{"flag":23,"item_type_id":32006,"quantity_destroyed":1},{"flag":94,"item_type_id":31718,"quantity_destroyed":1},{"flag":5,"item_type_id":12805,"quantity_dropped":2175},{"flag":21,"item_type_id":2281,"quantity_destroyed":1},{"flag":22,"item_type_id":3244,"quantity_destroyed":1},{"flag":13,"item_type_id":10190,"quantity_destroyed":1},{"flag":27,"item_type_id":12346,"quantity_destroyed":1},{"flag":32,"item_type_id":12801,"quantity_destroyed":66},{"flag":20,"item_type_id":2281,"quantity_dropped":1},{"flag":14,"item_type_id":10190,"quantity_destroyed":1},{"flag":28,"item_type_id":12346,"quantity_dropped":1},{"flag":29,"item_type_id":12801,"quantity_destroyed":66},{"flag":23,"item_type_id":3568,"quantity_destroyed":1},{"flag":27,"item_type_id":12801,"quantity_dropped":66},{"flag":5,"item_type_id":32006,"quantity_dropped":31},{"flag":29,"item_type_id":12346,"quantity_destroyed":1},{"flag":28,"item_type_id":12801,"quantity_destroyed":66},{"flag":30,"item_type_id":12346,"quantity_dropped":1},{"flag":92,"item_type_id":31718,"quantity_destroyed":1},{"flag":31,"item_type_id":12801,"quantity_dropped":66},{"flag":24,"item_type_id":12058,"quantity_destroyed":1},{"flag":5,"item_type_id":12801,"quantity_destroyed":2700},{"flag":93,"item_type_id":31790,"quantity_destroyed":1},{"flag":12,"item_type_id":10190,"quantity_dropped":1}],"position":{"x":-2.0116574327544174e+11,"y":-3.817402654503205e+10,"z":1.495841419995645e+11},"ship_type_id":16227},"war_id":607513}