{"attackers":[{"alliance_id":99001134,"character_id":94493523,"corporation_id":354495185,"damage_done":364,"final_blow":true,"security_status":3,"ship_type_id":29988,"weapon_type_id":3138},{"alliance_id":99001134,"character_id":96295777,"corporation_id":354495185,"damage_done":83,"security_status":4.3,"ship_type_id":17720,"weapon_type_id":17720}],"killmail_id":71242851,"killmail_time":"2018-07-14T09:22:58-07:00","solar_system_id":30003504,"victim":{"alliance_id":498125261,"character_id":2113913069,"corporation_id":98486683,"damage_taken":447,"items":[{"flag":89,"item_type_id":19534,"quantity_destroyed":1},{"flag":89,"item_type_id":19536,"quantity_destroyed":1},{"flag":89,"item_type_id":19535,"quantity_destroyed":1},{"flag":89,"item_type_id":9943,"quantity_destroyed":1}],"position":{"x":-2.7575420980955684e+12,"y":-4.7520878340289014e+11,"z":-3.0482973122097e+12},"ship_type_id":670},"war_id":605264}