{"attackers":[{"character_id":1613500455,"corporation_id":98407212,"damage_done":29960,"final_blow":true,"security_status":-7.7,"ship_type_id":24702,"weapon_type_id":2913},{"character_id":1409235210,"corporation_id":98407212,"damage_done":14042,"security_status":-3.7,"ship_type_id":24702,"weapon_type_id":24702}],"killmail_id":71243295,"killmail_time":"2018-07-14T09:51:18-07:00","solar_system_id":30000274,"victim":{"alliance_id":99005338,"character_id":2112445572,"corporation_id":98502864,"damage_taken":44002,"items":[{"flag":5,"item_type_id":8419,"quantity_dropped":1},{"flag":5,"item_type_id":232,"quantity_dropped":100},{"flag":5,"item_type_id":222,"quantity_dropped":100},{"flag":5,"item_type_id":5955,"quantity_destroyed":1},{"flag":5,"item_type_id":5282,"quantity_destroyed":1},{"flag":5,"item_type_id":8117,"quantity_dropped":1},{"flag":5,"item_type_id":236,"quantity_dropped":100},{"flag":5,"item_type_id":15331,"quantity_destroyed":5},{"flag":5,"item_type_id":15331,"quantity_dropped":4},{"flag":5,"item_type_id":205,"quantity_dropped":100},{"flag":5,"item_type_id":41056,"quantity_dropped":2},{"flag":5,"item_type_id":7293,"quantity_dropped":1},{"flag":5,"item_type_id":5141,"quantity_dropped":1},{"flag":5,"item_type_id":204,"quantity_dropped":200},{"flag":5,"item_type_id":238,"quantity_destroyed":100},{"flag":5,"item_type_id":6001,"quantity_destroyed":1},{"flag":5,"item_type_id":8635,"quantity_dropped":1},{"flag":5,"item_type_id":202,"quantity_dropped":100},{"flag":5,"item_type_id":221,"quantity_destroyed":100},{"flag":5,"item_type_id":5945,"quantity_destroyed":1},{"flag":5,"item_type_id":35662,"quantity_dropped":1},{"flag":5,"item_type_id":7451,"quantity_destroyed":2},{"flag":5,"item_type_id":33442,"quantity_destroyed":1}],"position":{"x":3.114624510879161e+11,"y":-8.71799192021051e+10,"z":2.0962344230973442e+10},"ship_type_id":33475}}