{"attackers":[{"character_id":298246483,"corporation_id":98265369,"damage_done":875,"final_blow":true,"security_status":4.2,"ship_type_id":17843,"weapon_type_id":2185}],"killmail_id":71246314,"killmail_time":"2018-07-14T12:17:44-07:00","solar_system_id":31001683,"victim":{"character_id":2113111973,"corporation_id":1000107,"damage_taken":875,"items":[{"flag":5,"item_type_id":30013,"quantity_dropped":8},{"flag":19,"item_type_id":22175,"quantity_dropped":1},{"flag":21,"item_type_id":434,"quantity_dropped":1},{"flag":11,"item_type_id":2046,"quantity_dropped":1},{"flag":93,"item_type_id":31201,"quantity_destroyed":1},{"flag":20,"item_type_id":22177,"quantity_dropped":1},{"flag":12,"item_type_id":1403,"quantity_dropped":1},{"flag":13,"item_type_id":1403,"quantity_destroyed":1},{"flag":22,"item_type_id":6135,"quantity_dropped":1},{"flag":27,"item_type_id":17938,"quantity_destroyed":1},{"flag":92,"item_type_id":31238,"quantity_destroyed":1}],"position":{"x":-1.4145530920827292e+11,"y":-9.9766304867663e+06,"z":1.45453175343535e+12},"ship_type_id":607}}