{"attackers":[{"alliance_id":99000814,"character_id":93246684,"corporation_id":98518919,"damage_done":3179,"security_status":-3.9,"ship_type_id":24483,"weapon_type_id":40559},{"alliance_id":99000814,"character_id":878591080,"corporation_id":98552348,"damage_done":1478,"final_blow":true,"security_status":0.3,"ship_type_id":23915,"weapon_type_id":40559}],"killmail_id":71244110,"killmail_time":"2018-07-14T10:32:39-07:00","solar_system_id":30000675,"victim":{"alliance_id":99007988,"character_id":93509823,"corporation_id":98384059,"damage_taken":4657,"items":[{"flag":5,"item_type_id":10631,"quantity_destroyed":1},{"flag":5,"item_type_id":10631,"quantity_dropped":3},{"flag":29,"item_type_id":21898,"quantity_dropped":134},{"flag":34,"item_type_id":2881,"quantity_dropped":1},{"flag":33,"item_type_id":21898,"quantity_dropped":134},{"flag":28,"item_type_id":22782,"quantity_dropped":1},{"flag":5,"item_type_id":21898,"quantity_dropped":2536},{"flag":31,"item_type_id":21898,"quantity_dropped":134},{"flag":31,"item_type_id":2881,"quantity_destroyed":1},{"flag":93,"item_type_id":31668,"quantity_destroyed":1},{"flag":32,"item_type_id":21898,"quantity_dropped":134},{"flag":33,"item_type_id":2881,"quantity_dropped":1},{"flag":22,"item_type_id":8517,"quantity_destroyed":1},{"flag":19,"item_type_id":5973,"quantity_destroyed":1},{"flag":30,"item_type_id":2881,"quantity_dropped":1},{"flag":27,"item_type_id":11370,"quantity_destroyed":1},{"flag":20,"item_type_id":5443,"quantity_dropped":1},{"flag":11,"item_type_id":2605,"quantity_dropped":1},{"flag":32,"item_type_id":2881,"quantity_destroyed":1},{"flag":21,"item_type_id":8517,"quantity_dropped":1},{"flag":34,"item_type_id":21898,"quantity_dropped":134},{"flag":5,"item_type_id":22778,"quantity_dropped":60},{"flag":28,"item_type_id":22778,"quantity_dropped":3},{"flag":30,"item_type_id":21898,"quantity_dropped":134},{"flag":29,"item_type_id":2881,"quantity_destroyed":1},{"flag":5,"item_type_id":179,"quantity_dropped":200},{"flag":12,"item_type_id":5839,"quantity_destroyed":1},{"flag":5,"item_type_id":22782,"quantity_destroyed":1},{"flag":92,"item_type_id":31183,"quantity_destroyed":1}],"position":{"x":1.5447123103308857e+12,"y":-4.143331244274785e+10,"z":-4.320399621680538e+10},"ship_type_id":22456}}