{"attackers":[{"alliance_id":937872513,"character_id":2113681158,"corporation_id":917701062,"damage_done":1630,"final_blow":true,"security_status":-2.6,"ship_type_id":33468,"weapon_type_id":33530},{"damage_done":614,"faction_id":500020,"ship_type_id":33508}],"killmail_id":71246214,"killmail_time":"2018-07-14T12:13:07-07:00","solar_system_id":30005319,"victim":{"alliance_id":937872513,"character_id":2113681158,"corporation_id":917701062,"damage_taken":2244,"items":[{"flag":94,"item_type_id":31213,"quantity_destroyed":1},{"flag":87,"item_type_id":2205,"quantity_destroyed":5},{"flag":14,"item_type_id":2048,"quantity_destroyed":1},{"flag":5,"item_type_id":15331,"quantity_dropped":1},{"flag":87,"item_type_id":2456,"quantity_dropped":5},{"flag":5,"item_type_id":30488,"quantity_destroyed":2},{"flag":5,"item_type_id":30488,"quantity_dropped":6},{"flag":11,"item_type_id":11269,"quantity_destroyed":1},{"flag":27,"item_type_id":11578,"quantity_dropped":1},{"flag":5,"item_type_id":33577,"quantity_dropped":8},{"flag":20,"item_type_id":22175,"quantity_destroyed":1},{"flag":21,"item_type_id":22177,"quantity_dropped":1},{"flag":22,"item_type_id":33180,"quantity_dropped":1},{"flag":28,"item_type_id":28758,"quantity_dropped":1},{"flag":93,"item_type_id":30987,"quantity_destroyed":1},{"flag":19,"item_type_id":6003,"quantity_destroyed":1},{"flag":13,"item_type_id":4405,"quantity_dropped":1},{"flag":5,"item_type_id":33539,"quantity_destroyed":19},{"flag":5,"item_type_id":33539,"quantity_dropped":14},{"flag":5,"item_type_id":6005,"quantity_dropped":1},{"flag":12,"item_type_id":1183,"quantity_dropped":1},{"flag":5,"item_type_id":33556,"quantity_destroyed":1,"singleton":2},{"flag":87,"item_type_id":2488,"quantity_dropped":5},{"flag":92,"item_type_id":31009,"quantity_destroyed":1}],"position":{"x":2.206920856417978e+12,"y":3.2900383800696854e+10,"z":-3.102120441658202e+11},"ship_type_id":33468}}