{"attackers":[{"alliance_id":99005382,"character_id":161684017,"corporation_id":98057065,"damage_done":1629,"final_blow":true,"security_status":-1.7,"ship_type_id":29990,"weapon_type_id":2969}],"killmail_id":71246037,"killmail_time":"2018-07-14T12:08:47-07:00","solar_system_id":30000142,"victim":{"alliance_id":99005338,"character_id":94304911,"corporation_id":98558506,"damage_taken":1629,"items":[{"flag":11,"item_type_id":22291,"quantity_dropped":1},{"flag":92,"item_type_id":26931,"quantity_destroyed":1},{"flag":19,"item_type_id":5973,"quantity_destroyed":1},{"flag":31,"item_type_id":11578,"quantity_destroyed":1},{"flag":29,"item_type_id":27359,"quantity_dropped":34},{"flag":13,"item_type_id":22291,"quantity_destroyed":1},{"flag":29,"item_type_id":8117,"quantity_dropped":1},{"flag":93,"item_type_id":31644,"quantity_destroyed":1},{"flag":30,"item_type_id":27914,"quantity_destroyed":1},{"flag":20,"item_type_id":5405,"quantity_destroyed":1},{"flag":28,"item_type_id":8117,"quantity_destroyed":1},{"flag":28,"item_type_id":27359,"quantity_dropped":34},{"flag":30,"item_type_id":27918,"quantity_dropped":1},{"flag":21,"item_type_id":19810,"quantity_destroyed":1},{"flag":27,"item_type_id":27359,"quantity_dropped":34},{"flag":12,"item_type_id":35771,"quantity_destroyed":1},{"flag":27,"item_type_id":8117,"quantity_destroyed":1}],"position":{"x":-1.0730339853327565e+11,"y":-1.8744981021427105e+10,"z":4.364890130689821e+11},"ship_type_id":12034},"war_id":596507}