{"attackers":[{"alliance_id":386292982,"character_id":94035714,"corporation_id":1698858600,"damage_done":7667,"final_blow":true,"security_status":-1.6,"ship_type_id":29986,"weapon_type_id":3025},{"alliance_id":386292982,"character_id":1591160690,"corporation_id":1698858600,"damage_done":2001,"security_status":-3,"ship_type_id":33818,"weapon_type_id":27371},{"alliance_id":933731581,"character_id":766197953,"corporation_id":735418530,"damage_done":805,"security_status":5,"ship_type_id":11393,"weapon_type_id":11393},{"alliance_id":933731581,"character_id":94394046,"corporation_id":98180098,"damage_done":562,"security_status":5,"ship_type_id":33816,"weapon_type_id":27361},{"alliance_id":933731581,"character_id":855293194,"corporation_id":735418530,"damage_done":364,"security_status":3.5,"ship_type_id":22456,"weapon_type_id":22456},{"alliance_id":386292982,"character_id":185306300,"corporation_id":1698858600,"damage_done":250,"security_status":0.2,"ship_type_id":11198,"weapon_type_id":11198},{"alliance_id":933731581,"character_id":303757882,"corporation_id":98333500,"damage_done":192,"security_status":4.7,"ship_type_id":11190,"weapon_type_id":2488},{"alliance_id":386292982,"character_id":1699627940,"corporation_id":1698858600,"security_status":-3.7,"ship_type_id":17928,"weapon_type_id":527},{"alliance_id":386292982,"character_id":96147236,"corporation_id":1698858600,"security_status":-1.3,"ship_type_id":17928,"weapon_type_id":17559},{"alliance_id":933731581,"character_id":93079234,"corporation_id":1975749457,"security_status":-0.1,"ship_type_id":22456,"weapon_type_id":5443},{"alliance_id":386292982,"character_id":1683191473,"corporation_id":1698858600,"security_status":-1.7,"ship_type_id":33818,"weapon_type_id":1877},{"alliance_id":933731581,"character_id":95586742,"corporation_id":98561380,"security_status":0.3,"ship_type_id":11198,"weapon_type_id":3244}],"killmail_id":71243634,"killmail_time":"2018-07-14T10:05:25-07:00","solar_system_id":30002105,"victim":{"alliance_id":99003214,"character_id":96833512,"corporation_id":98169165,"damage_taken":11841,"items":[{"flag":11,"item_type_id":10998,"quantity_dropped":1},{"flag":5,"item_type_id":15331,"quantity_dropped":3},{"flag":5,"item_type_id":33474,"quantity_destroyed":1},{"flag":34,"item_type_id":11577,"quantity_destroyed":1},{"flag":31,"item_type_id":25861,"quantity_dropped":1},{"flag":20,"item_type_id":3841,"quantity_destroyed":1},{"flag":19,"item_type_id":6005,"quantity_destroyed":1},{"flag":27,"item_type_id":25861,"quantity_destroyed":1},{"flag":28,"item_type_id":25861,"quantity_destroyed":1},{"flag":5,"item_type_id":25604,"quantity_dropped":4},{"flag":30,"item_type_id":25861,"quantity_destroyed":1},{"flag":12,"item_type_id":10998,"quantity_destroyed":1},{"flag":94,"item_type_id":31155,"quantity_destroyed":1},{"flag":93,"item_type_id":31155,"quantity_destroyed":1},{"flag":29,"item_type_id":25861,"quantity_destroyed":1},{"flag":5,"item_type_id":25589,"quantity_dropped":1},{"flag":13,"item_type_id":10998,"quantity_destroyed":1},{"flag":87,"item_type_id":23707,"quantity_dropped":5},{"flag":92,"item_type_id":31161,"quantity_destroyed":1},{"flag":33,"item_type_id":24348,"quantity_dropped":1},{"flag":32,"item_type_id":25861,"quantity_dropped":1},{"flag":5,"item_type_id":25601,"quantity_destroyed":1}],"position":{"x":-2.1819188360800308e+12,"y":3.17777382405542e+11,"z":-1.2634478726755735e+12},"ship_type_id":2998}}