{"attackers":[{"character_id":90372402,"corporation_id":98090476,"damage_done":1802,"security_status":-0.2,"ship_type_id":17918,"weapon_type_id":2629},{"alliance_id":99005382,"character_id":248872589,"corporation_id":98557686,"damage_done":1584,"final_blow":true,"security_status":-0.8,"ship_type_id":29990,"weapon_type_id":2969},{"character_id":96069434,"corporation_id":98450869,"damage_done":301,"security_status":0.6,"ship_type_id":17715,"weapon_type_id":27361},{"alliance_id":99004364,"character_id":615993731,"corporation_id":98380820,"security_status":-0.8,"ship_type_id":20125,"weapon_type_id":12267}],"killmail_id":71242463,"killmail_time":"2018-07-14T09:05:34-07:00","solar_system_id":31000790,"victim":{"character_id":95109064,"corporation_id":98465022,"damage_taken":3687,"items":[{"flag":143,"item_type_id":194,"quantity_dropped":100},{"flag":143,"item_type_id":261,"quantity_destroyed":1},{"flag":143,"item_type_id":184,"quantity_dropped":100},{"flag":143,"item_type_id":222,"quantity_dropped":2293},{"flag":143,"item_type_id":27441,"quantity_dropped":3862},{"flag":143,"item_type_id":27351,"quantity_dropped":248},{"flag":143,"item_type_id":227,"quantity_destroyed":100},{"flag":143,"item_type_id":195,"quantity_dropped":100},{"flag":143,"item_type_id":232,"quantity_dropped":100},{"flag":143,"item_type_id":27339,"quantity_destroyed":5232},{"flag":143,"item_type_id":32014,"quantity_destroyed":4},{"flag":143,"item_type_id":225,"quantity_dropped":100},{"flag":143,"item_type_id":33572,"quantity_dropped":400},{"flag":143,"item_type_id":27345,"quantity_destroyed":256},{"flag":143,"item_type_id":2512,"quantity_destroyed":100},{"flag":143,"item_type_id":27433,"quantity_destroyed":7},{"flag":19,"item_type_id":21857,"quantity_dropped":1},{"flag":143,"item_type_id":27387,"quantity_dropped":500},{"flag":11,"item_type_id":11640,"quantity_dropped":1},{"flag":143,"item_type_id":27447,"quantity_dropped":6430},{"flag":143,"item_type_id":234,"quantity_dropped":100},{"flag":143,"item_type_id":215,"quantity_dropped":100},{"flag":143,"item_type_id":35794,"quantity_dropped":1},{"flag":143,"item_type_id":29011,"quantity_dropped":1},{"flag":12,"item_type_id":1405,"quantity_dropped":1},{"flag":143,"item_type_id":2514,"quantity_destroyed":100},{"flag":143,"item_type_id":27435,"quantity_destroyed":2813},{"flag":143,"item_type_id":238,"quantity_destroyed":100},{"flag":143,"item_type_id":42839,"quantity_destroyed":1},{"flag":143,"item_type_id":243,"quantity_dropped":1},{"flag":143,"item_type_id":42838,"quantity_dropped":1},{"flag":143,"item_type_id":265,"quantity_dropped":100},{"flag":143,"item_type_id":258,"quantity_destroyed":1},{"flag":143,"item_type_id":27333,"quantity_destroyed":119},{"flag":143,"item_type_id":248,"quantity_destroyed":1},{"flag":143,"item_type_id":1822,"quantity_dropped":100},{"flag":143,"item_type_id":180,"quantity_destroyed":100},{"flag":143,"item_type_id":11287,"quantity_dropped":449},{"flag":143,"item_type_id":2506,"quantity_dropped":100},{"flag":143,"item_type_id":19970,"quantity_destroyed":1000},{"flag":143,"item_type_id":33571,"quantity_destroyed":400},{"flag":143,"item_type_id":27321,"quantity_destroyed":98},{"flag":143,"item_type_id":1820,"quantity_destroyed":100},{"flag":143,"item_type_id":223,"quantity_dropped":100},{"flag":143,"item_type_id":178,"quantity_dropped":100},{"flag":143,"item_type_id":33573,"quantity_dropped":400},{"flag":143,"item_type_id":1832,"quantity_destroyed":100},{"flag":143,"item_type_id":206,"quantity_dropped":200},{"flag":143,"item_type_id":33569,"quantity_dropped":500},{"flag":143,"item_type_id":216,"quantity_destroyed":100},{"flag":143,"item_type_id":35795,"quantity_destroyed":1},{"flag":20,"item_type_id":9660,"quantity_destroyed":1},{"flag":143,"item_type_id":42840,"quantity_dropped":1},{"flag":143,"item_type_id":187,"quantity_destroyed":100},{"flag":143,"item_type_id":27359,"quantity_dropped":256},{"flag":143,"item_type_id":29009,"quantity_dropped":1},{"flag":143,"item_type_id":11289,"quantity_destroyed":45},{"flag":143,"item_type_id":27353,"quantity_dropped":1136},{"flag":143,"item_type_id":28999,"quantity_destroyed":1},{"flag":143,"item_type_id":213,"quantity_dropped":100},{"flag":143,"item_type_id":27453,"quantity_destroyed":2878},{"flag":143,"item_type_id":27371,"quantity_dropped":1700},{"flag":143,"item_type_id":183,"quantity_dropped":200},{"flag":143,"item_type_id":189,"quantity_destroyed":100},{"flag":143,"item_type_id":27315,"quantity_destroyed":61},{"flag":13,"item_type_id":5631,"quantity_dropped":1}],"position":{"x":5.024347155708022e+12,"y":3.285702626413665e+08,"z":3.2832650806601616e+12},"ship_type_id":651}}